ai_prompt_game/__init__.py
ai_prompt_game/cli.py
ai_prompt_game/comparison.py
ai_prompt_game/game_engine.py
ai_prompt_game/image_generator.py
ai_prompt_game/utils.py
ai_prompt_game-1.1.0.dist-info/licenses/LICENSE
ai_prompt_game-1.1.0.dist-info/METADATA
ai_prompt_game-1.1.0.dist-info/WHEEL
ai_prompt_game-1.1.0.dist-info/entry_points.txt
ai_prompt_game-1.1.0.dist-info/top_level.txt
ai_prompt_game-1.1.0.dist-info/RECORD
